qaviton/__init__.py
qaviton/__main__.py
qaviton/crosstest.py
qaviton/exceptions.py
qaviton/heal.py
qaviton/locator.py
qaviton/navigator.py
qaviton/page.py
qaviton/schedualer.py
qaviton/settings.py
qaviton/steps.json
qaviton/version.py
qaviton/drivers/__init__.py
qaviton/drivers/mobile_driver.py
qaviton/drivers/webdriver.py
qaviton/drivers/xml_driver.py
qaviton/drivers/common/__init__.py
qaviton/drivers/common/functions.py
qaviton/drivers/common/webdriver.py
qaviton/drivers/common/webelement.py
qaviton/drivers/support/__init__.py
qaviton/drivers/support/expected_conditions.py
qaviton/fixtures/__init__.py
qaviton/fixtures/dependency.py
qaviton/fixtures/makereport.py
qaviton/scripts/__init__.py
qaviton/scripts/add_python_module_to_path.py
qaviton/scripts/create.py
qaviton/scripts/examples/__init__.py
qaviton/scripts/examples/new_project/__init__.py
qaviton/scripts/examples/new_project/conftest.py
qaviton/scripts/examples/new_project/config/__init__.py
qaviton/scripts/examples/new_project/config/locators.py
qaviton/scripts/examples/new_project/config/secret.py
qaviton/scripts/examples/new_project/config/supported_platforms.py
qaviton/scripts/examples/new_project/execute_tests/__init__.py
qaviton/scripts/examples/new_project/execute_tests/end_to_end_tests/__init__.py
qaviton/scripts/examples/new_project/pages/__init__.py
qaviton/scripts/examples/new_project/pages/home.py
qaviton/scripts/examples/new_project/pages/components/__init__.py
qaviton/scripts/examples/new_project/pages/components/page.py
qaviton/scripts/examples/new_project/services/__init__.py
qaviton/scripts/examples/new_project/services/app.py
qaviton/scripts/examples/simple_web/__init__.py
qaviton/scripts/examples/simple_web/conftest.py
qaviton/scripts/examples/simple_web/config/__init__.py
qaviton/scripts/examples/simple_web/config/locators.py
qaviton/scripts/examples/simple_web/config/secret.py
qaviton-0.1.3.dist-info/METADATA
qaviton-0.1.3.dist-info/RECORD
qaviton-0.1.3.dist-info/WHEEL
qaviton-0.1.3.dist-info/top_level.txt
