Metadata-Version: 2.1
Name: qaviton
Version: 0.1.3
Summary: python implementation of qaviton
Home-page: https://qaviton.com/
Author: Yehonadav Bar Elan
Author-email: yehonadav@Qaviton.com
License: Apache 2.0
Keywords: qaviton
Platform: UNKNOWN
Classifier: Development Status :: 3 - Alpha
Classifier: Programming Language :: Python
Classifier: Environment :: Console
Classifier: Environment :: MacOS X
Classifier: Environment :: Win32 (MS Windows)
Classifier: Intended Audience :: Developers
Classifier: Intended Audience :: Other Audience
Classifier: License :: OSI Approved :: Apache Software License
Classifier: Operating System :: OS Independent
Classifier: Topic :: Software Development :: Quality Assurance
Classifier: Topic :: Software Development :: Testing
Classifier: Topic :: Software Development :: Libraries :: Application Frameworks
Requires-Dist: Appium-Python-Client (>=0.28)
Requires-Dist: selenium (>=3.14.0)
Requires-Dist: Faker (>=0.8.17)
Requires-Dist: keyboard (>=0.13.2)
Requires-Dist: mouse (>=0.7.0)
Requires-Dist: imageio (>=2.3.0)
Requires-Dist: pytest (>=3.7.1)
Requires-Dist: pytest-xdist (>=1.22.5)
Requires-Dist: pytest-cov (>=2.5.1)
Requires-Dist: pytest-ordering (>=0.5)
Requires-Dist: pytest-forked (>=0.2)
Requires-Dist: threaders (>=0.2.13)
Requires-Dist: PyYAML (>=3.13)
Requires-Dist: requests (>=2.19.1)
